Canvect/__init__.py
Canvect/can_bus_handler.py
Canvect/ring_buffer.py
canvect-0.1.6.dist-info/LICENSE
canvect-0.1.6.dist-info/METADATA
canvect-0.1.6.dist-info/WHEEL
canvect-0.1.6.dist-info/top_level.txt
canvect-0.1.6.dist-info/RECORD
