Metadata-Version: 2.1
Name: canvect
Version: 0.1.6
Summary: Canvect is a Python package designed for sending and managing CAN (Controller Area Network) messages related to acceleration control. It provides a simple yet flexible API for creating and dispatching CAN messages, making it ideal for applications in automotive and industrial systems where CAN communication is essential.
Home-page: https://github.com/gnanesh-16/Canvect
Author: Gnanesh Balusa
Author-email: gnaneshbalusa016g@gmail.com
Classifier: Programming Language :: Python :: 3
Classifier: License :: OSI Approved :: MIT License
Classifier: Operating System :: OS Independent
Requires-Python: >=3.6
License-File: LICENSE
Requires-Dist: python-can
